Metadata-Version: 2.1
Name: EasyMongoManager
Version: 0.1
Summary: A simple interface for MongoDB interactions
Home-page: https://github.com/CREATIVE181/easy_mongodb
Author: CREATIVE
Author-email: sony.creative.tg1@gmail.com
Classifier: Programming Language :: Python :: 3.12
Classifier: License :: OSI Approved :: MIT License
Classifier: Operating System :: OS Independent
Requires-Python: >=3.6
License-File: LICENSE
Requires-Dist: pymongo
